{
  "name": "Behaviors",
  "class": "Behaviors",
  "functions": {
    "behaviorTriggers": {
      "description": {
        "tags": [
          {
            "type": "api",
            "visibility": "public"
          },
          {
            "type": "param",
            "types": [
              "<type>"
            ],
            "name": "behaviorTriggers",
            "description": "<description>",
            "optional": false,
            "typeStr": "<type>"
          },
          {
            "type": "param",
            "types": [
              "<type>"
            ],
            "name": "behaviors",
            "description": "<description>",
            "optional": false,
            "typeStr": "<type>"
          },
          {
            "type": "returns",
            "types": [
              "<type>"
            ],
            "description": "- <description>"
          }
        ],
        "description": {
          "full": "",
          "summary": "",
          "body": ""
        },
        "isPrivate": false,
        "api": {
          "type": "api",
          "visibility": "public"
        },
        "params": [
          {
            "type": "param",
            "types": [
              "<type>"
            ],
            "name": "behaviorTriggers",
            "description": "<description>",
            "optional": false,
            "typeStr": "<type>"
          },
          {
            "type": "param",
            "types": [
              "<type>"
            ],
            "name": "behaviors",
            "description": "<description>",
            "optional": false,
            "typeStr": "<type>"
          }
        ],
        "paramStr": "behaviorTriggers, behaviors"
      },
      "examples": [
        {
          "name": "<name>",
          "example": "<example>\n"
        }
      ]
    },
    "behaviorEvents": {
      "description": {
        "tags": [
          {
            "type": "api",
            "visibility": "public"
          },
          {
            "type": "param",
            "types": [
              "<type>"
            ],
            "name": "behaviorEvents",
            "description": "<description>",
            "optional": false,
            "typeStr": "<type>"
          },
          {
            "type": "param",
            "types": [
              "<type>"
            ],
            "name": "behaviors",
            "description": "<description>",
            "optional": false,
            "typeStr": "<type>"
          },
          {
            "type": "returns",
            "types": [
              "<type>"
            ],
            "description": "- <description>"
          }
        ],
        "description": {
          "full": "",
          "summary": "",
          "body": ""
        },
        "isPrivate": false,
        "api": {
          "type": "api",
          "visibility": "public"
        },
        "params": [
          {
            "type": "param",
            "types": [
              "<type>"
            ],
            "name": "behaviorEvents",
            "description": "<description>",
            "optional": false,
            "typeStr": "<type>"
          },
          {
            "type": "param",
            "types": [
              "<type>"
            ],
            "name": "behaviors",
            "description": "<description>",
            "optional": false,
            "typeStr": "<type>"
          }
        ],
        "paramStr": "behaviorEvents, behaviors"
      },
      "examples": [
        {
          "name": "<name>",
          "example": "<example>\n"
        }
      ]
    },
    "behaviorsLookup": {
      "description": {
        "tags": [
          {
            "type": "api",
            "visibility": "public"
          }
        ],
        "description": {
          "full": "",
          "summary": "",
          "body": ""
        },
        "isPrivate": false,
        "api": {
          "type": "api",
          "visibility": "public"
        },
        "params": [],
        "paramStr": ""
      },
      "examples": [
        {
          "name": "<name>",
          "example": "<example>\n"
        }
      ]
    },
    "getBehaviorClass": {
      "description": {
        "tags": [
          {
            "type": "api",
            "visibility": "public"
          },
          {
            "type": "param",
            "types": [
              "<type>"
            ],
            "name": "options",
            "description": "<description>",
            "optional": false,
            "typeStr": "<type>"
          },
          {
            "type": "param",
            "types": [
              "<type>"
            ],
            "name": "key",
            "description": "<description>",
            "optional": false,
            "typeStr": "<type>"
          },
          {
            "type": "returns",
            "types": [
              "<type>"
            ],
            "description": "- <description>"
          }
        ],
        "description": {
          "full": "",
          "summary": "",
          "body": ""
        },
        "isPrivate": false,
        "api": {
          "type": "api",
          "visibility": "public"
        },
        "params": [
          {
            "type": "param",
            "types": [
              "<type>"
            ],
            "name": "options",
            "description": "<description>",
            "optional": false,
            "typeStr": "<type>"
          },
          {
            "type": "param",
            "types": [
              "<type>"
            ],
            "name": "key",
            "description": "<description>",
            "optional": false,
            "typeStr": "<type>"
          }
        ],
        "paramStr": "options, key"
      },
      "examples": [
        {
          "name": "<name>",
          "example": "<example>\n"
        }
      ]
    },
    "parseBehaviors": {
      "description": {
        "tags": [
          {
            "type": "api",
            "visibility": "public"
          },
          {
            "type": "param",
            "types": [
              "<type>"
            ],
            "name": "view",
            "description": "<description>",
            "optional": false,
            "typeStr": "<type>"
          },
          {
            "type": "param",
            "types": [
              "<type>"
            ],
            "name": "behaviors",
            "description": "<description>",
            "optional": false,
            "typeStr": "<type>"
          },
          {
            "type": "returns",
            "types": [
              "<type>"
            ],
            "description": "- <description>"
          }
        ],
        "description": {
          "full": "",
          "summary": "",
          "body": ""
        },
        "isPrivate": false,
        "api": {
          "type": "api",
          "visibility": "public"
        },
        "params": [
          {
            "type": "param",
            "types": [
              "<type>"
            ],
            "name": "view",
            "description": "<description>",
            "optional": false,
            "typeStr": "<type>"
          },
          {
            "type": "param",
            "types": [
              "<type>"
            ],
            "name": "behaviors",
            "description": "<description>",
            "optional": false,
            "typeStr": "<type>"
          }
        ],
        "paramStr": "view, behaviors"
      },
      "examples": [
        {
          "name": "<name>",
          "example": "<example>\n"
        }
      ]
    },
    "wrap": {
      "description": {
        "tags": [
          {
            "type": "api",
            "visibility": "public"
          },
          {
            "type": "param",
            "types": [
              "<type>"
            ],
            "name": "view",
            "description": "<description>",
            "optional": false,
            "typeStr": "<type>"
          },
          {
            "type": "param",
            "types": [
              "<type>"
            ],
            "name": "behaviors",
            "description": "<description>",
            "optional": false,
            "typeStr": "<type>"
          },
          {
            "type": "param",
            "types": [
              "<type>"
            ],
            "name": "methodNames",
            "description": "<description>",
            "optional": false,
            "typeStr": "<type>"
          }
        ],
        "description": {
          "full": "",
          "summary": "",
          "body": ""
        },
        "isPrivate": false,
        "api": {
          "type": "api",
          "visibility": "public"
        },
        "params": [
          {
            "type": "param",
            "types": [
              "<type>"
            ],
            "name": "view",
            "description": "<description>",
            "optional": false,
            "typeStr": "<type>"
          },
          {
            "type": "param",
            "types": [
              "<type>"
            ],
            "name": "behaviors",
            "description": "<description>",
            "optional": false,
            "typeStr": "<type>"
          },
          {
            "type": "param",
            "types": [
              "<type>"
            ],
            "name": "methodNames",
            "description": "<description>",
            "optional": false,
            "typeStr": "<type>"
          }
        ],
        "paramStr": "view, behaviors, methodNames"
      },
      "examples": [
        {
          "name": "<name>",
          "example": "<example>\n"
        }
      ]
    },
    "buildBehaviorTriggers": {
      "description": {
        "tags": [
          {
            "type": "api",
            "visibility": "public"
          },
          {
            "type": "returns",
            "types": [
              "<type>"
            ],
            "description": "- <description>"
          }
        ],
        "description": {
          "full": "",
          "summary": "",
          "body": ""
        },
        "isPrivate": false,
        "api": {
          "type": "api",
          "visibility": "public"
        },
        "params": [],
        "paramStr": ""
      },
      "examples": [
        {
          "name": "<name>",
          "example": "<example>\n"
        }
      ]
    },
    "_buildTriggerHandlersForBehavior": {
      "description": {
        "tags": [
          {
            "type": "api",
            "visibility": "private"
          },
          {
            "type": "param",
            "types": [
              "<type>"
            ],
            "name": "behavior",
            "description": "<description>",
            "optional": false,
            "typeStr": "<type>"
          },
          {
            "type": "param",
            "types": [
              "<type>"
            ],
            "name": "i",
            "description": "<description>",
            "optional": false,
            "typeStr": "<type>"
          }
        ],
        "description": {
          "full": "",
          "summary": "",
          "body": ""
        },
        "isPrivate": true,
        "api": {
          "type": "api",
          "visibility": "private"
        },
        "params": [
          {
            "type": "param",
            "types": [
              "<type>"
            ],
            "name": "behavior",
            "description": "<description>",
            "optional": false,
            "typeStr": "<type>"
          },
          {
            "type": "param",
            "types": [
              "<type>"
            ],
            "name": "i",
            "description": "<description>",
            "optional": false,
            "typeStr": "<type>"
          }
        ],
        "paramStr": "behavior, i"
      },
      "examples": [
        {
          "name": "<name>",
          "example": "<example>\n"
        }
      ]
    },
    "_setHandlerForBehavior": {
      "description": {
        "tags": [
          {
            "type": "api",
            "visibility": "private"
          },
          {
            "type": "param",
            "types": [
              "<type>"
            ],
            "name": "behavior",
            "description": "<description>",
            "optional": false,
            "typeStr": "<type>"
          },
          {
            "type": "param",
            "types": [
              "<type>"
            ],
            "name": "i",
            "description": "<description>",
            "optional": false,
            "typeStr": "<type>"
          },
          {
            "type": "param",
            "types": [
              "<type>"
            ],
            "name": "eventName",
            "description": "<description>",
            "optional": false,
            "typeStr": "<type>"
          },
          {
            "type": "param",
            "types": [
              "<type>"
            ],
            "name": "trigger",
            "description": "<description>",
            "optional": false,
            "typeStr": "<type>"
          }
        ],
        "description": {
          "full": "",
          "summary": "",
          "body": ""
        },
        "isPrivate": true,
        "api": {
          "type": "api",
          "visibility": "private"
        },
        "params": [
          {
            "type": "param",
            "types": [
              "<type>"
            ],
            "name": "behavior",
            "description": "<description>",
            "optional": false,
            "typeStr": "<type>"
          },
          {
            "type": "param",
            "types": [
              "<type>"
            ],
            "name": "i",
            "description": "<description>",
            "optional": false,
            "typeStr": "<type>"
          },
          {
            "type": "param",
            "types": [
              "<type>"
            ],
            "name": "eventName",
            "description": "<description>",
            "optional": false,
            "typeStr": "<type>"
          },
          {
            "type": "param",
            "types": [
              "<type>"
            ],
            "name": "trigger",
            "description": "<description>",
            "optional": false,
            "typeStr": "<type>"
          }
        ],
        "paramStr": "behavior, i, eventName, trigger"
      },
      "examples": [
        {
          "name": "<name>",
          "example": "<example>\n"
        }
      ]
    }
  },
  "properties": {
    "_view": {
      "examples": [],
      "description": {
        "tags": [
          {
            "type": "type",
            "types": [
              "<type>"
            ]
          }
        ],
        "description": {
          "full": "<description>\n",
          "summary": "<description>\n",
          "body": ""
        },
        "isPrivate": false,
        "params": [],
        "paramStr": ""
      }
    },
    "_viewUI": {
      "examples": [],
      "description": {
        "tags": [
          {
            "type": "type",
            "types": [
              "<type>"
            ]
          }
        ],
        "description": {
          "full": "<description>\n",
          "summary": "<description>\n",
          "body": ""
        },
        "isPrivate": false,
        "params": [],
        "paramStr": ""
      }
    },
    "_behaviors": {
      "examples": [],
      "description": {
        "tags": [
          {
            "type": "type",
            "types": [
              "<type>"
            ]
          }
        ],
        "description": {
          "full": "<description>\n",
          "summary": "<description>\n",
          "body": ""
        },
        "isPrivate": false,
        "params": [],
        "paramStr": ""
      }
    },
    "_triggers": {
      "examples": [],
      "description": {
        "tags": [
          {
            "type": "type",
            "types": [
              "<type>"
            ]
          }
        ],
        "description": {
          "full": "<description>\n",
          "summary": "<description>\n",
          "body": ""
        },
        "isPrivate": false,
        "params": [],
        "paramStr": ""
      }
    }
  },
  "examples": [],
  "description": "",
  "constructor": {}
}